MANIFEST.in
setup.py
cmd/lab2blog
lab2blog/__init__.py
lab2blog/custom.css
lab2blog.egg-info/PKG-INFO
lab2blog.egg-info/SOURCES.txt
lab2blog.egg-info/dependency_links.txt
lab2blog.egg-info/top_level.txt