Metadata-Version: 1.2
Name: lab2blog
Version: 0.1
Summary: Jupyter Lab to HTML
Home-page: UNKNOWN
Author: Yeison Cardona
Author-email: yeisoneng@gmail.com
Maintainer: Yeison Cardona
Maintainer-email: yeisoneng@gmail.com
License: BSD License
Download-URL: https://bitbucket.org/yeisoneng/lab2blog/downloads/
Platform: UNKNOWN
